README.txt
setup.py
AtomicWrite.egg-info/PKG-INFO
AtomicWrite.egg-info/SOURCES.txt
AtomicWrite.egg-info/dependency_links.txt
AtomicWrite.egg-info/entry_points.txt
AtomicWrite.egg-info/not-zip-safe
AtomicWrite.egg-info/top_level.txt
atomic/__init__.py
atomic/writer.py