Metadata-Version: 1.0
Name: AtomicWrite
Version: 0.1
Summary: write file contents atomically in one operation
Home-page: http://k0s.org/hg/AtomicWrite
Author: Jeff Hammel
Author-email: k0scist@gmail.com
License: MIT
Platform: UNKNOWN
